{"version":2,"runId":"29205403768","runFile":"2026-07-12T19-16-22-331Z-29205403768.json","status":"passed","date":"2026-07-12T19:16:22.331Z","durationMs":0,"commitSha":"459dbe86b34892ccd10e805c53322d80bdc3e186","commitShortSha":"459dbe8","commitMessage":"Workflow run","author":"mzbrau","total":0,"passed":0,"failed":0,"skipped":0,"diagnostics":{"errors":11,"warnings":76,"notes":26,"bySource":{"msbuild":{"errors":9,"warnings":66},"sarif":{"errors":2,"warnings":10}}},"diagnosticsFile":"2026-07-12T19-16-22-331Z-29205403768.diagnostics.json","timing":{"slowestStep":"build › Build"},"timingFile":"2026-07-12T19-16-22-331Z-29205403768.timing.json"}