{
  "version": 1,
  "branchKey": "pr-50",
  "branchLabel": "PR #50",
  "updatedAt": "2026-07-08T21:06:23.543Z",
  "runs": [
    {
      "runId": "28975533770",
      "workflowRunId": 28975533770,
      "status": "passed",
      "date": "2026-07-08T21:06:19.469Z",
      "durationMs": 10368,
      "total": 360,
      "passed": 360,
      "failed": 0,
      "skipped": 0,
      "commitSha": "47700dce4bd819faafd1486bbef92633bf208d13",
      "commitShortSha": "47700dc",
      "commitMessage": "Workflow run",
      "author": "mzbrau",
      "runFile": "2026-07-08T21-06-19-469Z-28975533770.json"
    },
    {
      "runId": "28971528351",
      "workflowRunId": 28971528351,
      "status": "passed",
      "date": "2026-07-08T19:58:25.421Z",
      "durationMs": 10346,
      "total": 360,
      "passed": 360,
      "failed": 0,
      "skipped": 0,
      "commitSha": "5545e7c0c8ae57e506107267d81f6a7aec2b0f87",
      "commitShortSha": "5545e7c",
      "commitMessage": "Workflow run",
      "author": "mzbrau",
      "runFile": "2026-07-08T19-58-25-421Z-28971528351.json"
    },
    {
      "runId": "28970797209",
      "workflowRunId": 28970797209,
      "status": "failed",
      "date": "2026-07-08T19:46:16.099Z",
      "durationMs": 10418,
      "total": 360,
      "passed": 359,
      "failed": 1,
      "skipped": 0,
      "commitSha": "a1b89373457f4f165b722bf6c46f0035fad27749",
      "commitShortSha": "a1b8937",
      "commitMessage": "Workflow run",
      "author": "mzbrau",
      "runFile": "2026-07-08T19-46-16-099Z-28970797209.json"
    },
    {
      "runId": "28897583237",
      "workflowRunId": 28897583237,
      "status": "failed",
      "date": "2026-07-07T20:49:23.805Z",
      "durationMs": 10928,
      "total": 360,
      "passed": 356,
      "failed": 4,
      "skipped": 0,
      "commitSha": "40d9358c557a573f2da6e3740ac46339181b32b1",
      "commitShortSha": "40d9358",
      "commitMessage": "Workflow run",
      "author": "mzbrau",
      "runFile": "2026-07-07T20-49-23-805Z-28897583237.json"
    },
    {
      "runId": "28897038891",
      "workflowRunId": 28897038891,
      "status": "failed",
      "date": "2026-07-07T20:39:50.572Z",
      "durationMs": 10110,
      "total": 360,
      "passed": 355,
      "failed": 5,
      "skipped": 0,
      "commitSha": "737a41b83f5f6e9f6f5d7f8398a3560efb8978d8",
      "commitShortSha": "737a41b",
      "commitMessage": "Workflow run",
      "author": "mzbrau",
      "runFile": "2026-07-07T20-39-50-572Z-28897038891.json"
    }
  ]
}